pycreatedgmlgraph/__init__.py
pycreatedgmlgraph-1.0.dist-info/METADATA
pycreatedgmlgraph-1.0.dist-info/WHEEL
pycreatedgmlgraph-1.0.dist-info/top_level.txt
pycreatedgmlgraph-1.0.dist-info/RECORD
